dalybms/__init__.py
dalybms/daly_bms.py
dalybms/daly_bms_bluetooth.py
dalybms/daly_sinowealth.py
dalybms/error_codes.py
dalybms-0.5.0.data/scripts/daly-bms-cli
dalybms-0.5.0.dist-info/LICENSE
dalybms-0.5.0.dist-info/METADATA
dalybms-0.5.0.dist-info/WHEEL
dalybms-0.5.0.dist-info/top_level.txt
dalybms-0.5.0.dist-info/RECORD
