Metadata-Version: 2.1
Name: dalybms
Version: 0.5.0
Summary: Client for Daly BMS
Home-page: https://github.com/dreadnought/python-daly-bms
Author: Patrick Salecker
Author-email: mail@salecker.org
License: MIT
Platform: UNKNOWN
Classifier: License :: OSI Approved :: MIT License
Classifier: Programming Language :: Python :: 3
Classifier: Programming Language :: Python :: 3.6
Classifier: Programming Language :: Python :: 3.7
Classifier: Programming Language :: Python :: 3.8
License-File: LICENSE
